{
    "$schema": "http://json-schema.org/draft-03/schema",
    "$license": [
        "http://www.apache.org/licenses/LICENSE-2.0"
    ],
    "id": "#",
    "type": "object",
    "javaType": "org.apache.streams.datasift.DatasiftPush",
    "javaInterfaces": ["java.io.Serializable"],
    "properties": {
        "id": {
            "type": "string"
        },
        "hash": {
            "type": "string"
        },
        "hash_type": {
            "type": "string"
        },
        "count": {
            "type": "long"
        },
        "delivered_at": {
            "type": "string",
            "format": "date-time"
        },
        "interactions": {
            "type": "array",
            "items": {
                "type": "object",
                "javaType": "org.apache.streams.datasift.Datasift"
            }
        }
    }
}