{
    "$schema": "http://json-schema.org/draft-03/schema",
    "$license": [
        "http://www.apache.org/licenses/LICENSE-2.0"
    ],
    "id": "#",
    "type": "object",
    "title": "object",
    "javaType": "org.apache.streams.pojo.json.StreamsTaskCounterBroadcast",
    "javaInterfaces": ["java.io.Serializable"],
    "extends": {
        "$ref": "./Broadcast.json"
    },
    "description": "Snapshot of a Stream Task Counter",
    "properties": {
        "errorRate": {
            "type": "double",
            "description": "Rate of failed items"
        },
        "numEmitted": {
            "type": "integer",
            "description": "Number of items that have been emitted"
        },
        "numReceived": {
            "type": "integer",
            "description": "Number of items this Task has received"
        },
        "numUnhandledErrors": {
            "type": "integer",
            "description": "Number of unhandled errors"
        },
        "avgTime": {
            "type": "double",
            "description": "Average amount of time an item spent in this Task"
        },
        "maxTime": {
            "type": "integer",
            "description": "Longest amount of time an item spent in this Task"
        },
        "name": {
            "type": "string",
            "description": "Name of the MBean"
        }
    }
}