<?xml version="1.0" encoding="UTF-8"?>
<beans xmlns="http://www.springframework.org/schema/beans"
       xmlns:xsi="http://www.w3.org/2001/XMLSchema-instance"
       xmlns:osgi="http://www.springframework.org/schema/osgi"
       xsi:schemaLocation="http://www.springframework.org/schema/beans
	http://www.springframework.org/schema/beans/spring-beans.xsd
    http://www.springframework.org/schema/osgi
    http://www.springframework.org/schema/osgi/spring-osgi.xsd">


    <osgi:reference id="activityPublisherRegistration" interface="org.apache.streams.osgi.components.ActivityPublisherRegistration" />

    <osgi:reference id="activityConsumerWarehouse" interface="org.apache.streams.osgi.components.activityconsumer.ActivityConsumerWarehouse" />



    <bean id="activityRegistrationProcessor" class="org.apache.streams.messaging.processors.ActivityRegistrationProcessor"/>


    <bean id="activityRouter" class="org.apache.streams.messaging.routers.impl.ActivityConsumerRouter">
          <property name="activityConsumerWarehouse" ref="activityConsumerWarehouse"/>
        <property name="camelContext" ref="context"/>
    </bean>

    <bean id="jmsConnectionFactory"
          class="org.apache.activemq.ActiveMQConnectionFactory">
        <property name="brokerURL" value="tcp://localhost:61616" />
    </bean>

    <bean id="pooledConnectionFactory"
          class="org.apache.activemq.pool.PooledConnectionFactory" init-method="start" destroy-method="stop">
        <property name="maxConnections" value="8" />
        <property name="connectionFactory" ref="jmsConnectionFactory" />
    </bean>

    <bean id="jmsConfig"
          class="org.apache.camel.component.jms.JmsConfiguration">
        <property name="connectionFactory" ref="pooledConnectionFactory"/>
        <property name="concurrentConsumers" value="10"/>
    </bean>

    <bean id="activemq"
          class="org.apache.activemq.camel.component.ActiveMQComponent">
        <property name="configuration" ref="jmsConfig"/>
    </bean>


</beans>